pytuber/__init__.py
pytuber/cli.py
pytuber/exceptions.py
pytuber/iso3166.py
pytuber/storage.py
pytuber/utils.py
pytuber/version.py
pytuber/core/__init__.py
pytuber/core/models.py
pytuber/core/params.py
pytuber/core/services.py
pytuber/core/commands/__init__.py
pytuber/core/commands/cmd_add.py
pytuber/core/commands/cmd_autocomplete.py
pytuber/core/commands/cmd_clean.py
pytuber/core/commands/cmd_fetch.py
pytuber/core/commands/cmd_list.py
pytuber/core/commands/cmd_push.py
pytuber/core/commands/cmd_quota.py
pytuber/core/commands/cmd_remove.py
pytuber/core/commands/cmd_setup.py
pytuber/core/commands/cmd_show.py
pytuber/lastfm/__init__.py
pytuber/lastfm/models.py
pytuber/lastfm/params.py
pytuber/lastfm/services.py
pytuber/lastfm/commands/__init__.py
pytuber/lastfm/commands/cmd_add.py
pytuber/lastfm/commands/cmd_fetch.py
pytuber/lastfm/commands/cmd_setup.py
pytuber-22.5.dist-info/LICENSE
pytuber-22.5.dist-info/METADATA
pytuber-22.5.dist-info/WHEEL
pytuber-22.5.dist-info/entry_points.txt
pytuber-22.5.dist-info/top_level.txt
pytuber-22.5.dist-info/RECORD
