Metadata-Version: 2.1
Name: pytuber
Version: 22.5
Summary: Manage youtube music playlists
Home-page: https://github.com/tefra/pytuber
Author: Christodoulos Tsoulloftas
Author-email: "chris@komposta.net",
License: MIT
Project-URL: Source, https://github.com/tefra/pytuber
Project-URL: Documentation, https://pytuber.readthedocs.io/
Keywords: youtube,music,playlist,last.fm,cli
Platform: UNKNOWN
Classifier: Intended Audience :: Developers
Classifier: License :: OSI Approved :: MIT License
Classifier: Operating System :: OS Independent
Classifier: Programming Language :: Python
Classifier: Programming Language :: Python :: 3
Classifier: Programming Language :: Python :: 3 :: Only
Classifier: Programming Language :: Python :: 3.6
Classifier: Programming Language :: Python :: 3.7
Classifier: Programming Language :: Python :: 3.8
Classifier: Programming Language :: Python :: 3.9
Classifier: Programming Language :: Python :: 3.10
Classifier: Programming Language :: Python :: Implementation :: CPython
Requires-Python: >=3.6
License-File: LICENSE
Requires-Dist: click (>=5.0)
Requires-Dist: click-completion (>=0.5.1)
Requires-Dist: google-api-python-client (>=1.7.8)
Requires-Dist: google-auth (>=1.6.3)
Requires-Dist: google-auth-oauthlib (>=0.3.0)
Requires-Dist: lxml (>=4.3.3)
Requires-Dist: pydrag (>=22.5)
Requires-Dist: tabulate[widechars] (>=0.8.3)
Requires-Dist: yaspin (>=0.14.2)
Provides-Extra: dev
Requires-Dist: Pygments ; extra == 'dev'
Requires-Dist: check-manifest ; extra == 'dev'
Requires-Dist: codecov ; extra == 'dev'
Requires-Dist: pre-commit ; extra == 'dev'
Requires-Dist: pytest ; extra == 'dev'
Requires-Dist: pytest-cov ; extra == 'dev'
Requires-Dist: tox ; extra == 'dev'
Provides-Extra: docs
Requires-Dist: sphinx ; extra == 'docs'
Requires-Dist: sphinx-rtd-theme ; extra == 'docs'
Requires-Dist: sphinxcontrib-programoutput ; extra == 'docs'
